pytext/__init__.py
pytext/builtin_task.py
pytext/main.py
pytext/workflow.py
pytext/common/__init__.py
pytext/common/constants.py
pytext/config/__init__.py
pytext/config/component.py
pytext/config/contextual_intent_slot.py
pytext/config/doc_classification.py
pytext/config/field_config.py
pytext/config/module_config.py
pytext/config/pair_classification.py
pytext/config/pytext_config.py
pytext/config/serialize.py
pytext/data/__init__.py
pytext/data/bptt_lm_data_handler.py
pytext/data/compositional_data_handler.py
pytext/data/contextual_intent_slot_data_handler.py
pytext/data/data_handler.py
pytext/data/disjoint_multitask_data_handler.py
pytext/data/doc_classification_data_handler.py
pytext/data/joint_data_handler.py
pytext/data/language_model_data_handler.py
pytext/data/pair_classification_data_handler.py
pytext/data/seq_data_handler.py
pytext/data/data_structures/__init__.py
pytext/data/data_structures/annotation.py
pytext/data/featurizer/__init__.py
pytext/data/featurizer/featurizer.py
pytext/data/featurizer/simple_featurizer.py
pytext/exporters/__init__.py
pytext/exporters/exporter.py
pytext/fields/__init__.py
pytext/fields/char_field.py
pytext/fields/dict_field.py
pytext/fields/field.py
pytext/fields/pretrained_model_embedding_field.py
pytext/fields/text_field_with_special_unk.py
pytext/loss/__init__.py
pytext/loss/loss.py
pytext/metric_reporters/__init__.py
pytext/metric_reporters/channel.py
pytext/metric_reporters/classification_metric_reporter.py
pytext/metric_reporters/compositional_metric_reporter.py
pytext/metric_reporters/disjoint_multitask_metric_reporter.py
pytext/metric_reporters/intent_slot_detection_metric_reporter.py
pytext/metric_reporters/language_model_metric_reporter.py
pytext/metric_reporters/metric_reporter.py
pytext/metric_reporters/word_tagging_metric_reporter.py
pytext/metrics/__init__.py
pytext/metrics/intent_slot_metrics.py
pytext/metrics/language_model_metrics.py
pytext/models/__init__.py
pytext/models/crf.py
pytext_nlp_test-0.1.2.dist-info/LICENSE
pytext_nlp_test-0.1.2.dist-info/METADATA
pytext_nlp_test-0.1.2.dist-info/WHEEL
pytext_nlp_test-0.1.2.dist-info/entry_points.txt
pytext_nlp_test-0.1.2.dist-info/top_level.txt
pytext_nlp_test-0.1.2.dist-info/RECORD
