Metadata-Version: 2.1
Name: pytext-nlp-test
Version: 0.1.2
Summary: pytorch modeling framework and model zoo for text models
Home-page: https://github.com/facebookresearch/PyText
Author: Facebook
Author-email: UNKNOWN
License: BSD
Platform: UNKNOWN
Requires-Dist: click
Requires-Dist: future
Requires-Dist: hypothesis
Requires-Dist: joblib
Requires-Dist: numpy
Requires-Dist: onnx
Requires-Dist: pandas
Requires-Dist: requests
Requires-Dist: scipy
Requires-Dist: torchtext
Requires-Dist: tensorboardX
